pare/__init__.py
pare/client.py
pare/console.py
pare/constants.py
pare/errors.py
pare/login.py
pare/models.py
pare/settings.py
pare/cli/__init__.py
pare/cli/delete.py
pare/cli/deploy.py
pare/cli/main.py
pare/cli/status.py
pare/cli/tests/__init__.py
pare/cli/tests/sample.py
pare/cli/tests/test_deploy.py
pare/cli/tests/test_main.py
pare/sdk/__init__.py
pare/sdk/main.py
pare/sdk/tests/__init__.py
pare/sdk/tests/test_sdk.py
pare-0.3.2.dist-info/LICENSE
pare-0.3.2.dist-info/METADATA
pare-0.3.2.dist-info/WHEEL
pare-0.3.2.dist-info/entry_points.txt
pare-0.3.2.dist-info/top_level.txt
pare-0.3.2.dist-info/RECORD
